<?xml version="1.0" encoding="UTF-8"?>

<ValueSet xmlns="http://hl7.org/fhir">
  <id value="v2-0265"/>
  <meta>
    <profile value="http://hl7.org/fhir/StructureDefinition/valueset-shareable-definition"/>
  </meta>
  <text>
    <status value="additional"/>
    <div xmlns="http://www.w3.org/1999/xhtml">
      <p>Specialty Type</p>

      <table class="grid">
        <tr>
          <td>
            <b>Code</b>
          </td>
          <td>
            <b>Description</b>
          </td>
          <td>
            <b>Nederlands (Dutch)</b>
          </td>
          <td>
            <b>Comment</b>
          </td>
          <td>
            <b>Version</b>
          </td>
        </tr>
        <tr>
          <td>ALC
            <a name="ALC"> </a>
          </td>
          <td>Allergy</td>
          <td>Allergie</td>
          <td/>
          <td>added v2.3</td>
        </tr>
        <tr>
          <td>AMB
            <a name="AMB"> </a>
          </td>
          <td>Ambulatory</td>
          <td>Dagbehandeling</td>
          <td/>
          <td>added v2.3</td>
        </tr>
        <tr>
          <td>CAN
            <a name="CAN"> </a>
          </td>
          <td>Cancer</td>
          <td>Kanker</td>
          <td/>
          <td>added v2.3</td>
        </tr>
        <tr>
          <td>CAR
            <a name="CAR"> </a>
          </td>
          <td>Coronary/cardiac care</td>
          <td>Cornaire/hartzorg</td>
          <td/>
          <td>added v2.3</td>
        </tr>
        <tr>
          <td>CCR
            <a name="CCR"> </a>
          </td>
          <td>Critical care</td>
          <td>Kritieke zorg</td>
          <td/>
          <td>added v2.3</td>
        </tr>
        <tr>
          <td>CHI
            <a name="CHI"> </a>
          </td>
          <td>Chiropractic</td>
          <td>Chiropractisch</td>
          <td/>
          <td>added v2.3</td>
        </tr>
        <tr>
          <td>EDI
            <a name="EDI"> </a>
          </td>
          <td>Education</td>
          <td>Onderwijs</td>
          <td/>
          <td>added v2.3</td>
        </tr>
        <tr>
          <td>EMR
            <a name="EMR"> </a>
          </td>
          <td>Emergency</td>
          <td>Spoed</td>
          <td/>
          <td>added v2.3</td>
        </tr>
        <tr>
          <td>FPC
            <a name="FPC"> </a>
          </td>
          <td>Family planning</td>
          <td>Gezinsplanning</td>
          <td/>
          <td>added v2.3</td>
        </tr>
        <tr>
          <td>INT
            <a name="INT"> </a>
          </td>
          <td>Intensive care</td>
          <td>Intensieve care</td>
          <td/>
          <td>added v2.3</td>
        </tr>
        <tr>
          <td>ISO
            <a name="ISO"> </a>
          </td>
          <td>Isolation</td>
          <td>Isolatie</td>
          <td/>
          <td>added v2.3</td>
        </tr>
        <tr>
          <td>NAT
            <a name="NAT"> </a>
          </td>
          <td>Naturopathic</td>
          <td>Natuurgeneeskundig</td>
          <td/>
          <td>added v2.3</td>
        </tr>
        <tr>
          <td>NBI
            <a name="NBI"> </a>
          </td>
          <td>Newborn, nursery, infants</td>
          <td>Nieuwgeborene, kinderkamer, zuigelingen</td>
          <td/>
          <td>added v2.3</td>
        </tr>
        <tr>
          <td>OBG
            <a name="OBG"> </a>
          </td>
          <td>Obstetrics, gynecology</td>
          <td>Obstetrie, gynaecologie</td>
          <td/>
          <td>added v2.3</td>
        </tr>
        <tr>
          <td>OBS
            <a name="OBS"> </a>
          </td>
          <td>Observation</td>
          <td>Observaties</td>
          <td/>
          <td>added v2.3</td>
        </tr>
        <tr>
          <td>OTH
            <a name="OTH"> </a>
          </td>
          <td>Other specialty</td>
          <td>Ander specialisme</td>
          <td/>
          <td>added v2.3</td>
        </tr>
        <tr>
          <td>PED
            <a name="PED"> </a>
          </td>
          <td>Pediatrics</td>
          <td>Pediatrie</td>
          <td/>
          <td>added v2.3</td>
        </tr>
        <tr>
          <td>PHY
            <a name="PHY"> </a>
          </td>
          <td>General/family practice</td>
          <td>Algemeen/gezinspraktijk</td>
          <td/>
          <td>added v2.3</td>
        </tr>
        <tr>
          <td>PIN
            <a name="PIN"> </a>
          </td>
          <td>Pediatric/neonatal intensive care</td>
          <td>Pediatrie/neonatale intensive care</td>
          <td/>
          <td>added v2.3</td>
        </tr>
        <tr>
          <td>PPS
            <a name="PPS"> </a>
          </td>
          <td>Pediatric psychiatric</td>
          <td>Psychiatrische pediatrie</td>
          <td/>
          <td>added v2.3</td>
        </tr>
        <tr>
          <td>PRE
            <a name="PRE"> </a>
          </td>
          <td>Pediatric rehabilitation</td>
          <td>Pediatrische revalidatie</td>
          <td/>
          <td>added v2.3</td>
        </tr>
        <tr>
          <td>PSI
            <a name="PSI"> </a>
          </td>
          <td>Psychiatric intensive care</td>
          <td>Psychiatrische intensive care</td>
          <td/>
          <td>added v2.3</td>
        </tr>
        <tr>
          <td>PSY
            <a name="PSY"> </a>
          </td>
          <td>Psychiatric</td>
          <td>Psychiatrisch</td>
          <td/>
          <td>added v2.3</td>
        </tr>
        <tr>
          <td>REH
            <a name="REH"> </a>
          </td>
          <td>Rehabilitation</td>
          <td>Revalidatie</td>
          <td/>
          <td>added v2.3</td>
        </tr>
        <tr>
          <td>SUR
            <a name="SUR"> </a>
          </td>
          <td>Surgery</td>
          <td>Chirurgie</td>
          <td/>
          <td>added v2.3</td>
        </tr>
        <tr>
          <td>WIC
            <a name="WIC"> </a>
          </td>
          <td>Walk-in clinic</td>
          <td>Inloopkliniek</td>
          <td/>
          <td>added v2.3</td>
        </tr>
      </table>

    </div>
  </text>
  <url value="http://hl7.org/fhir/ValueSet/v2-0265"/>
  <version value="2.8.2"/>
  <name value="v2 Specialty Type"/>
  <status value="active"/>
  <experimental value="true"/>
  <publisher value="HL7, Inc"/>
  <contact>
    <telecom>
      <system value="other"/>
      <value value="http://hl7.org"/>
    </telecom>
  </contact>
  <description value="FHIR Value set/code system definition for HL7 v2 table 0265 ( Specialty Type)"/>
  <compose>
    <include>
      <system value="http://hl7.org/fhir/v2/0265"/>
    </include>
  </compose>
</ValueSet>